{
  "+p_xml": "version=\"1.0\" encoding=\"utf-8\"",
  "+p_xml-stylesheet": "type='text/xsl' href='STIG_unclass.xsl'",
  "Benchmark": {
    "+@xmlns:dc": "http://purl.org/dc/elements/1.1/",
    "+@xmlns:xsi": "http://www.w3.org/2001/XMLSchema-instance",
    "+@xmlns:cpe": "http://cpe.mitre.org/language/2.0",
    "+@xmlns:xhtml": "http://www.w3.org/1999/xhtml",
    "+@xmlns:dsig": "http://www.w3.org/2000/09/xmldsig#",
    "+@xsi:schemaLocation": "http://checklists.nist.gov/xccdf/1.1 http://nvd.nist.gov/schema/xccdf-1.1.4.xsd http://cpe.mitre.org/dictionary/2.0 http://cpe.mitre.org/files/cpe-dictionary_2.1.xsd",
    "+@id": "zOS_CLSuperSession_for_ACF2_STIG",
    "+@xml:lang": "en",
    "+@xmlns": "http://checklists.nist.gov/xccdf/1.1",
    "status": {
      "+content": "accepted",
      "+@date": "2024-12-16"
    },
    "title": "z/OS CL/SuperSession for ACF2 Security Technical Implementation Guide",
    "description": "This Security Technical Implementation Guide is published as a tool to improve the security of Department of Defense (DOD) information systems. The requirements are derived from the National Institute of Standards and Technology (NIST) 800-53 and related documents. Comments or proposed revisions to this document should be sent via email to the following address: disa.stig_spt@mail.mil.",
    "notice": {
      "+@id": "terms-of-use",
      "+@xml:lang": "en"
    },
    "front-matter": {
      "+@xml:lang": "en"
    },
    "rear-matter": {
      "+@xml:lang": "en"
    },
    "reference": {
      "+@href": "https://cyber.mil",
      "publisher": "DISA",
      "source": "STIG.DOD.MIL"
    },
    "plain-text": [
      {
        "+content": "Release: 1 Benchmark Date: 30 Jan 2025",
        "+@id": "release-info"
      },
      {
        "+content": "3.5",
        "+@id": "generator"
      },
      {
        "+content": "1.10.0",
        "+@id": "conventionsVersion"
      }
    ],
    "version": "7",
    "Profile": [
      {
        "+@id": "MAC-1_Classified",
        "title": "I - Mission Critical Classified",
        "description": "<ProfileDescription></ProfileDescription>",
        "select": [
          {
            "+@idref": "V-224282",
            "+@selected": "true"
          },
          {
            "+@idref": "V-224283",
            "+@selected": "true"
          },
          {
            "+@idref": "V-224284",
            "+@selected": "true"
          },
          {
            "+@idref": "V-224285",
            "+@selected": "true"
          },
          {
            "+@idref": "V-224286",
            "+@selected": "true"
          },
          {
            "+@idref": "V-224287",
            "+@selected": "true"
          },
          {
            "+@idref": "V-224288",
            "+@selected": "true"
          }
        ]
      },
      {
        "+@id": "MAC-1_Public",
        "title": "I - Mission Critical Public",
        "description": "<ProfileDescription></ProfileDescription>",
        "select": [
          {
            "+@idref": "V-224282",
            "+@selected": "true"
          },
          {
            "+@idref": "V-224283",
            "+@selected": "true"
          },
          {
            "+@idref": "V-224284",
            "+@selected": "true"
          },
          {
            "+@idref": "V-224285",
            "+@selected": "true"
          },
          {
            "+@idref": "V-224286",
            "+@selected": "true"
          },
          {
            "+@idref": "V-224287",
            "+@selected": "true"
          },
          {
            "+@idref": "V-224288",
            "+@selected": "true"
          }
        ]
      },
      {
        "+@id": "MAC-1_Sensitive",
        "title": "I - Mission Critical Sensitive",
        "description": "<ProfileDescription></ProfileDescription>",
        "select": [
          {
            "+@idref": "V-224282",
            "+@selected": "true"
          },
          {
            "+@idref": "V-224283",
            "+@selected": "true"
          },
          {
            "+@idref": "V-224284",
            "+@selected": "true"
          },
          {
            "+@idref": "V-224285",
            "+@selected": "true"
          },
          {
            "+@idref": "V-224286",
            "+@selected": "true"
          },
          {
            "+@idref": "V-224287",
            "+@selected": "true"
          },
          {
            "+@idref": "V-224288",
            "+@selected": "true"
          }
        ]
      },
      {
        "+@id": "MAC-2_Classified",
        "title": "II - Mission Support Classified",
        "description": "<ProfileDescription></ProfileDescription>",
        "select": [
          {
            "+@idref": "V-224282",
            "+@selected": "true"
          },
          {
            "+@idref": "V-224283",
            "+@selected": "true"
          },
          {
            "+@idref": "V-224284",
            "+@selected": "true"
          },
          {
            "+@idref": "V-224285",
            "+@selected": "true"
          },
          {
            "+@idref": "V-224286",
            "+@selected": "true"
          },
          {
            "+@idref": "V-224287",
            "+@selected": "true"
          },
          {
            "+@idref": "V-224288",
            "+@selected": "true"
          }
        ]
      },
      {
        "+@id": "MAC-2_Public",
        "title": "II - Mission Support Public",
        "description": "<ProfileDescription></ProfileDescription>",
        "select": [
          {
            "+@idref": "V-224282",
            "+@selected": "true"
          },
          {
            "+@idref": "V-224283",
            "+@selected": "true"
          },
          {
            "+@idref": "V-224284",
            "+@selected": "true"
          },
          {
            "+@idref": "V-224285",
            "+@selected": "true"
          },
          {
            "+@idref": "V-224286",
            "+@selected": "true"
          },
          {
            "+@idref": "V-224287",
            "+@selected": "true"
          },
          {
            "+@idref": "V-224288",
            "+@selected": "true"
          }
        ]
      },
      {
        "+@id": "MAC-2_Sensitive",
        "title": "II - Mission Support Sensitive",
        "description": "<ProfileDescription></ProfileDescription>",
        "select": [
          {
            "+@idref": "V-224282",
            "+@selected": "true"
          },
          {
            "+@idref": "V-224283",
            "+@selected": "true"
          },
          {
            "+@idref": "V-224284",
            "+@selected": "true"
          },
          {
            "+@idref": "V-224285",
            "+@selected": "true"
          },
          {
            "+@idref": "V-224286",
            "+@selected": "true"
          },
          {
            "+@idref": "V-224287",
            "+@selected": "true"
          },
          {
            "+@idref": "V-224288",
            "+@selected": "true"
          }
        ]
      },
      {
        "+@id": "MAC-3_Classified",
        "title": "III - Administrative Classified",
        "description": "<ProfileDescription></ProfileDescription>",
        "select": [
          {
            "+@idref": "V-224282",
            "+@selected": "true"
          },
          {
            "+@idref": "V-224283",
            "+@selected": "true"
          },
          {
            "+@idref": "V-224284",
            "+@selected": "true"
          },
          {
            "+@idref": "V-224285",
            "+@selected": "true"
          },
          {
            "+@idref": "V-224286",
            "+@selected": "true"
          },
          {
            "+@idref": "V-224287",
            "+@selected": "true"
          },
          {
            "+@idref": "V-224288",
            "+@selected": "true"
          }
        ]
      },
      {
        "+@id": "MAC-3_Public",
        "title": "III - Administrative Public",
        "description": "<ProfileDescription></ProfileDescription>",
        "select": [
          {
            "+@idref": "V-224282",
            "+@selected": "true"
          },
          {
            "+@idref": "V-224283",
            "+@selected": "true"
          },
          {
            "+@idref": "V-224284",
            "+@selected": "true"
          },
          {
            "+@idref": "V-224285",
            "+@selected": "true"
          },
          {
            "+@idref": "V-224286",
            "+@selected": "true"
          },
          {
            "+@idref": "V-224287",
            "+@selected": "true"
          },
          {
            "+@idref": "V-224288",
            "+@selected": "true"
          }
        ]
      },
      {
        "+@id": "MAC-3_Sensitive",
        "title": "III - Administrative Sensitive",
        "description": "<ProfileDescription></ProfileDescription>",
        "select": [
          {
            "+@idref": "V-224282",
            "+@selected": "true"
          },
          {
            "+@idref": "V-224283",
            "+@selected": "true"
          },
          {
            "+@idref": "V-224284",
            "+@selected": "true"
          },
          {
            "+@idref": "V-224285",
            "+@selected": "true"
          },
          {
            "+@idref": "V-224286",
            "+@selected": "true"
          },
          {
            "+@idref": "V-224287",
            "+@selected": "true"
          },
          {
            "+@idref": "V-224288",
            "+@selected": "true"
          }
        ]
      }
    ],
    "Group": [
      {
        "+@id": "V-224282",
        "title": "SRG-OS-000018",
        "description": "<GroupDescription></GroupDescription>",
        "Rule": {
          "+@id": "SV-224282r1041215_rule",
          "+@weight": "10.0",
          "+@severity": "medium",
          "version": "ZCLS0040",
          "title": "CL/SuperSession profile options are set improperly.",
          "description": "<VulnDiscussion>Product configuration/parameters control the security and operational characteristics of products. If these parameter values are improperly specified, security and operational controls may be weakened. This exposure may threaten the availability of the product applications, and compromise the confidentiality of customer data.</VulnDiscussion><FalsePositives></FalsePositives><FalseNegatives></FalseNegatives><Documentable>false</Documentable><Mitigations></Mitigations><SeverityOverrideGuidance></SeverityOverrideGuidance><PotentialImpacts></PotentialImpacts><ThirdPartyTools></ThirdPartyTools><MitigationControl></MitigationControl><Responsibility></Responsibility><IAControls></IAControls>",
          "reference": {
            "title": "DPMS Target zOS CLSuperSession for ACF2",
            "publisher": "DISA",
            "type": "DPMS Target",
            "subject": "zOS CLSuperSession for ACF2",
            "identifier": "4117"
          },
          "ident": [
            {
              "+content": "SV-27197",
              "+@system": "http://cyber.mil/legacy"
            },
            {
              "+content": "V-18014",
              "+@system": "http://cyber.mil/legacy"
            },
            {
              "+content": "CCI-000057",
              "+@system": "http://cyber.mil/cci"
            },
            {
              "+content": "CCI-000381",
              "+@system": "http://cyber.mil/cci"
            }
          ],
          "fixtext": {
            "+content": "The systems programmer and ISSO will review all session manager security parameters and control options for compliance with the requirements of the z/OS STIG Addendum Required CL/SuperSession Common Profile Options and Required CL/SuperSession Profile Options Tables. Verify that the options are set properly.",
            "+@fixref": "F-25943r1041214_fix"
          },
          "fix": {
            "+@id": "F-25943r1041214_fix"
          },
          "check": {
            "+@system": "C-25955r1041213_chk",
            "check-content-ref": {
              "+@href": "zOS_CLSuperSession_for_ACF2_STIG.xml",
              "+@name": "M"
            },
            "check-content": "a) The following steps are necessary for reviewing the CL/SuperSession options:\n\n1) Request online access from the site administrator to view CL/SuperSession parameter settings.\n2) Once access to the CL/SuperSession Main Menu has been obtained, select the option for the ADMINISTRATOR menu.\n3) From the ADMINISTRATOR menu, select the option for the PROFILE SELECTION menu.\n4) From the PROFILE SELECTION menu, select the View GLOBAL Profile option.\n5) After selection of the View GLOBAL Profile option, the Update GLOBAL Profile menu appears. From this menu select the profile to be reviewed:\n\n- To view the Common profile select: _Common\n- To view the SUPERSESSION profile select: _SupSess\n\nAutomated Analysis\nRefer to the following report produced by the z/OS Data Collection:\n\n- PDI(ZCLS0040)\n\nb) Compare the security parameters as specified in the Required CL/SuperSession Common Profile Options and Required CL/SuperSession Profile Options Tables in the z/OS STIG Addendum against the CL/SuperSession Profile options.\n\nc) If all options as specified in the Required CL/SuperSession Common Profile Options and Required CL/SuperSession Profile Options Tables in the z/OS STIG Addendum are in effect, there is no finding.\n\nd) If any of the options as specified in the Required CL/SuperSession Common Profile Options and Required CL/SuperSession Profile Options Tables in the z/OS STIG Addendum is not in effect, this is a finding."
          }
        }
      },
      {
        "+@id": "V-224283",
        "title": "SRG-OS-000018",
        "description": "<GroupDescription></GroupDescription>",
        "Rule": {
          "+@id": "SV-224283r1041217_rule",
          "+@weight": "10.0",
          "+@severity": "medium",
          "version": "ZCLS0041",
          "title": "CL/SuperSession must be properly configured to generate SMF records for audit trail and accounting reports.",
          "description": "<VulnDiscussion>Product configuration/parameters control the security and operational characteristics of products. If these parameter values are improperly specified, security and operational controls may be weakened. This exposure may threaten the availability of the product applications and compromise the confidentiality of customer data.</VulnDiscussion><FalsePositives></FalsePositives><FalseNegatives></FalseNegatives><Documentable>false</Documentable><Mitigations></Mitigations><SeverityOverrideGuidance></SeverityOverrideGuidance><PotentialImpacts></PotentialImpacts><ThirdPartyTools></ThirdPartyTools><MitigationControl></MitigationControl><Responsibility></Responsibility><IAControls></IAControls>",
          "reference": {
            "title": "DPMS Target zOS CLSuperSession for ACF2",
            "publisher": "DISA",
            "type": "DPMS Target",
            "subject": "zOS CLSuperSession for ACF2",
            "identifier": "4117"
          },
          "ident": [
            {
              "+content": "SV-27198",
              "+@system": "http://cyber.mil/legacy"
            },
            {
              "+content": "V-22689",
              "+@system": "http://cyber.mil/legacy"
            },
            {
              "+content": "CCI-000172",
              "+@system": "http://cyber.mil/cci"
            },
            {
              "+content": "CCI-000381",
              "+@system": "http://cyber.mil/cci"
            },
            {
              "+content": "CCI-003938",
              "+@system": "http://cyber.mil/cci"
            }
          ],
          "fixtext": {
            "+content": "Ensure the Session Manager generates SMF records for audit trail and accounting reports.\n\nTo provide an audit trail of user activity in CL/SuperSession, configure the Network Accounting Facility (NAF) to require SMF recording of accounting and audit data. Accounting to the journal data set is optional at the discretion of the site. To accomplish this for version 3 of CL/SuperSession, configure the following NAF startup parameters in the KLKINNAF member of the RLSPARM initialization parameter library as follows:\n\nDSNAME= dsname - Name of the NAF journal data set. Required only if the site is collecting accounting and audit data in the journal data set in addition to the SMF data.\n\nMOD - If the journal data set is used, this parameter should be set to ensure that logging data in the data set is not overwritten.\n\nSMF=nnn - SMF record number. This field is mandatory to ensure that CL/SuperSession data is always written to the SMF files.",
            "+@fixref": "F-25944r952245_fix"
          },
          "fix": {
            "+@id": "F-25944r952245_fix"
          },
          "check": {
            "+@system": "C-25956r1041216_chk",
            "check-content-ref": {
              "+@href": "zOS_CLSuperSession_for_ACF2_STIG.xml",
              "+@name": "M"
            },
            "check-content": "a) Version 3 of CL/SuperSession\nReview the member KLKINNAF in the TLVPARM DD statement concatenation of the CL/SuperSession STC procedure to determine SMF number. (This member is located in SYS3.OMEGAMON.qualifier.RLSPARM.)\n\nVersion 2 of CL/SuperSession\nReview the member KLVINNAF in the TLVPARM DD statement concatenation of the CL/SuperSession STC procedure to determine SMF number. (This member is located in SYS3.OMEGAMON.qualifier.RLSPARM.)\n\nRefer to the following report produced by the z/OS Data Collection:\n\n- EXAM.RPT(SMFOPTS)\n\nAutomated Analysis (Currently there is no automation for version 3 of CL/SuperSession)\nRefer to the following report produced by the z/OS Data Collection:\n\n- PDI(ZCLS0041)\n\nb) If the SMF= field specifies an SMF record number, review the SMFOPTS report to verify SMF is writing that record type.\n\nc) If SMF is writing the record number specified by SMF=, there is no finding.\n\nd) If the SMF= field does not specify an SMF record number, or SMF is not writing the record number specified by SMF=, this is a finding."
          }
        }
      },
      {
        "+@id": "V-224284",
        "title": "SRG-OS-000080",
        "description": "<GroupDescription></GroupDescription>",
        "Rule": {
          "+@id": "SV-224284r1041220_rule",
          "+@weight": "10.0",
          "+@severity": "medium",
          "version": "ZCLSA000",
          "title": "CL/SuperSession Install data sets must be properly protected.",
          "description": "<VulnDiscussion>CL/SuperSession Install data sets provide the capability to use privileged functions and/or have access to sensitive data. Failure to properly restrict access to their data sets could result in violating the integrity of the base product which could result in compromising the operating system or sensitive data.</VulnDiscussion><FalsePositives></FalsePositives><FalseNegatives></FalseNegatives><Documentable>false</Documentable><Mitigations></Mitigations><SeverityOverrideGuidance></SeverityOverrideGuidance><PotentialImpacts></PotentialImpacts><ThirdPartyTools></ThirdPartyTools><MitigationControl></MitigationControl><Responsibility></Responsibility><IAControls></IAControls>",
          "reference": {
            "title": "DPMS Target zOS CLSuperSession for ACF2",
            "publisher": "DISA",
            "type": "DPMS Target",
            "subject": "zOS CLSuperSession for ACF2",
            "identifier": "4117"
          },
          "ident": [
            {
              "+content": "V-16932",
              "+@system": "http://cyber.mil/legacy"
            },
            {
              "+content": "SV-27073",
              "+@system": "http://cyber.mil/legacy"
            },
            {
              "+content": "CCI-001499",
              "+@system": "http://cyber.mil/cci"
            },
            {
              "+content": "CCI-002234",
              "+@system": "http://cyber.mil/cci"
            }
          ],
          "fixtext": {
            "+content": "Ensure that update and allocate access to CL/SuperSession install data sets are limited to systems programmers only, and all update and allocate access is logged. Auditors should have READ access.\n\nThe installing systems programmer will identify and document the product data sets and categorize them according to who will have update and alter access and if required that all update and allocate access is logged. The installing systems programmer will identify if any additional groups have update access for specific data sets, and once documented will work with the ISSO to see that they are properly restricted to the ACP (Access Control Program ) active on the system.\n\nThe following dataset are an example of data sets to be protected: \nSYS2.OMEGAMON\nSYS2.OMEGAMON.V-.TLSLOAD\nSYS2.OMEGAMON.V-.TLVLOAD\nSYS3.OMEGAMON\nSYS3.OMEGAMON.RLSLOAD\n\nThe following commands are provided as an example for implementing dataset controls: \n\n$KEY(SYS2)\nOMEGAMON.- UID(syspaudt) R(A) W(L) A(L) E(A)\nOMEGAMON.V-.TLSLOAD UID(syspaudt) R(A) W(L) A(L) E(A) \nOMEGAMON.V-.TLVLOAD UID(syspaudt) R(A) W(L) A(L) E(A) \nOMEGAMON.- UID(audtaudt) R(A) E(A)\n\n$KEY(SYS3)\nOMEGAMON.- UID(syspaudt) R(A) W(L) A(L) E(A)\nOMEGAMON.RLSLOAD UID(syspaudt) R(A) W(L) A(L) E(A) \nOMEGAMON.- UID(audtaudt) R(A) E(A)",
            "+@fixref": "F-25945r1041219_fix"
          },
          "fix": {
            "+@id": "F-25945r1041219_fix"
          },
          "check": {
            "+@system": "C-25957r1041218_chk",
            "check-content-ref": {
              "+@href": "zOS_CLSuperSession_for_ACF2_STIG.xml",
              "+@name": "M"
            },
            "check-content": "a) Refer to the following report produced by the Data Set and Resource Data Collection:\n\n- SENSITVE.RPT(KLSRPT) \n\nAutomated Analysis:\nRefer to the following report produced by the Data Set and Resource Data Collection:\n\n- PDI(ZCLS0000)\n\nb) Verify that access to the CL/SuperSession Install data sets are properly restricted.\n\n___ The ACF2 data set rules for the data sets does not restrict UPDATE and/or ALTER access to systems programming personnel.\n\n___ The ACF2 data set rules for the data sets does not specify that all (i.e., failures and successes) UPDATE and/or ALTER access will be logged.\n\nc) If all of the above are untrue, there is no finding.\n\nd) If any of the above is true, this is a finding."
          }
        }
      },
      {
        "+@id": "V-224285",
        "title": "SRG-OS-000259",
        "description": "<GroupDescription></GroupDescription>",
        "Rule": {
          "+@id": "SV-224285r958616_rule",
          "+@weight": "10.0",
          "+@severity": "medium",
          "version": "ZCLSA001",
          "title": "CL/SuperSession STC data sets must be properly protected.",
          "description": "<VulnDiscussion>CL/SuperSession STC data sets provide the capability to use privileged functions and/or have access to sensitive data. Failure to properly restrict access to their data sets could result in violating the integrity of the base product which could result in compromising the operating system or sensitive data.</VulnDiscussion><FalsePositives></FalsePositives><FalseNegatives></FalseNegatives><Documentable>false</Documentable><Mitigations></Mitigations><SeverityOverrideGuidance></SeverityOverrideGuidance><PotentialImpacts></PotentialImpacts><ThirdPartyTools></ThirdPartyTools><MitigationControl></MitigationControl><Responsibility></Responsibility><IAControls></IAControls>",
          "reference": {
            "title": "DPMS Target zOS CLSuperSession for ACF2",
            "publisher": "DISA",
            "type": "DPMS Target",
            "subject": "zOS CLSuperSession for ACF2",
            "identifier": "4117"
          },
          "ident": [
            {
              "+content": "SV-27093",
              "+@system": "http://cyber.mil/legacy"
            },
            {
              "+content": "V-17067",
              "+@system": "http://cyber.mil/legacy"
            },
            {
              "+content": "CCI-001499",
              "+@system": "http://cyber.mil/cci"
            }
          ],
          "fixtext": {
            "+content": "Ensure that WRITE and/or greater access to CL/SuperSession STC data sets are limited to system programmers and CL/SuperSession STC only. Read access can be given to auditors and authorized users.\n\nThe installing systems programmer will identify and document the product data sets and categorize them according to who will have WRITE and/or greater access and if required that all WRITE and/or greater access is logged. The installing systems programmer will identify if any additional groups have WRITE and/or greater access for specific data sets, and once documented will work with the ISSO to ensure they are properly restricted to the ACP (Access Control Program) active on the system.\n\nNote: The data sets and/or data set prefixes identified below are examples of a possible installation. The actual data sets and/or prefixes are determined when the product is actually installed on a system through the product's installation guide and can be site specific. \n\nThe following dataset are an example of data sets to be protected:\nSYS3.OMEGAMON.RLSNAF\nSYS3.OMEGAMON.RLSNAM\nSYS3.OMEGAMON.RLSTDB\nSYS3.OMEGAMON.RLSVLOG\n\nThe following commands are provided as an example for implementing dataset controls: \n\n$KEY(SYS3)\nOMEGAMON.RLSNAF UID(*) R(A) E(A)\nOMEGAMON.RLSNAF UID(audtaudt) R(A) E(A)\nOMEGAMON.RLSNAF UID(syspaudt) R(A) W(A) A(A) E(A)\nOMEGAMON.RLSNAF UID(stc KLS) R(A) W(A) A(A) E(A)\nOMEGAMON.RLSNAM UID(*) R(A) E(A)\nOMEGAMON.RLSNAM UID(audtaudt) R(A) E(A)\nOMEGAMON.RLSNAM UID(syspaudt) R(A) W(A) A(A) E(A)\nOMEGAMON.RLSNAM UID(stc KLS) R(A) W(A) A(A) E(A)\nOMEGAMON.RLSTDB UID(*) R(A) E(A)\nOMEGAMON.RLSTDB UID(audtaudt) R(A) E(A)\nOMEGAMON.RLSTDB UID(syspaudt) R(A) W(A) A(A) E(A)\nOMEGAMON.RLSTDB UID(stc KLS) R(A) W(A) A(A) E(A)\nOMEGAMON.RLSVLOG UID(*) R(A) E(A)\nOMEGAMON.RLSVLOG UID(audtaudt) R(A) E(A)\nOMEGAMON.RLSVLOG UID(syspaudt) R(A) W(A) A(A) E(A)\nOMEGAMON.RLSVLOG UID(stc KLS) R(A) W(A) A(A) E(A)",
            "+@fixref": "F-25946r868108_fix"
          },
          "fix": {
            "+@id": "F-25946r868108_fix"
          },
          "check": {
            "+@system": "C-25958r868107_chk",
            "check-content-ref": {
              "+@href": "zOS_CLSuperSession_for_ACF2_STIG.xml",
              "+@name": "M"
            },
            "check-content": "Refer to the following report produced by the Data Set and Resource Data Collection:\n\n- SENSITVE.RPT(KLSSTC)\n\nAutomated Analysis:\nRefer to the following report produced by the Data Set and Resource Data Collection:\n\n- PDI(ZCLS0001)\n\nVerify that the accesses to the CL/SuperSession STC data sets are properly restricted. If the following guidance is true, this is not a finding.\n\n___ The ACF2 data set access authorizations restrict READ access to auditors and authorized users.\n\n___ The ACF2 data set access authorizations restrict WRITE and/or greater access to systems programming personnel.\n\n___ The ACF2 data set rules for the data sets does not restrict WRITE and/or greater access to the product STC(s) and/or batch job(s)."
          }
        }
      },
      {
        "+@id": "V-224286",
        "title": "SRG-OS-000104",
        "description": "<GroupDescription></GroupDescription>",
        "Rule": {
          "+@id": "SV-224286r958482_rule",
          "+@weight": "10.0",
          "+@severity": "medium",
          "version": "ZCLSA030",
          "title": "CL/SuperSession Started Task name is not properly identified / defined to the system ACP.",
          "description": "<VulnDiscussion>CL/SuperSession requires a started task that will be restricted to certain resources, datasets and other system functions. By defining the started task as a userid to the system ACP, It allows the ACP to control the access and authorized users that require these capabilities. Failure to properly control these capabilities, could compromise of the operating system environment, ACP, and customer data.</VulnDiscussion><FalsePositives></FalsePositives><FalseNegatives></FalseNegatives><Documentable>false</Documentable><Mitigations></Mitigations><SeverityOverrideGuidance></SeverityOverrideGuidance><PotentialImpacts></PotentialImpacts><ThirdPartyTools></ThirdPartyTools><MitigationControl></MitigationControl><Responsibility></Responsibility><IAControls></IAControls>",
          "reference": {
            "title": "DPMS Target zOS CLSuperSession for ACF2",
            "publisher": "DISA",
            "type": "DPMS Target",
            "subject": "zOS CLSuperSession for ACF2",
            "identifier": "4117"
          },
          "ident": [
            {
              "+content": "SV-28590",
              "+@system": "http://cyber.mil/legacy"
            },
            {
              "+content": "V-17452",
              "+@system": "http://cyber.mil/legacy"
            },
            {
              "+content": "CCI-000764",
              "+@system": "http://cyber.mil/cci"
            }
          ],
          "fixtext": {
            "+content": "The Systems Programmer and IAO will ensure that the started task for CL/SuperSession is properly defined.\n\nReview all session manager security parameters and control options for compliance. Develop a plan of action and implement the changes as specified.\n\nDefine the started task userid KLS for CL/SuperSession.\n\nExample:\n\nINSERT KLS NAME(STC, CL/SuperSession) MUSASS NO-SMC STC",
            "+@fixref": "F-25947r519729_fix"
          },
          "fix": {
            "+@id": "F-25947r519729_fix"
          },
          "check": {
            "+@system": "C-25959r519728_chk",
            "check-content-ref": {
              "+@href": "zOS_CLSuperSession_for_ACF2_STIG.xml",
              "+@name": "M"
            },
            "check-content": "a)\tRefer to the following report produced by the ACF2 Data Collection:\n\n-\tACF2CMDS.RPT(ATTSTC)\n\nb)\tIf the logonid for the CL/SUPERSESSION started task includes MUSASS and NO-SMC, there is NO FINDING.\n\nc)\tIf the logonid for the CL/SUPERSESSION started task does not include MUSASS and/or NO-SMC, this is a FINDING."
          }
        }
      },
      {
        "+@id": "V-224287",
        "title": "SRG-OS-000018",
        "description": "<GroupDescription></GroupDescription>",
        "Rule": {
          "+@id": "SV-224287r1041222_rule",
          "+@weight": "10.0",
          "+@severity": "medium",
          "version": "ZCLSA042",
          "title": "CL/SuperSession KLVINNAM member must be configured in accordance with security requirements.",
          "description": "<VulnDiscussion>CL/SuperSession configuration/parameters control the security and operational characteristics of products. If these parameter values are improperly specified, security and operational controls may be weakened. This exposure may threaten the availability of the product applications, and compromise the confidentiality of customer data.</VulnDiscussion><FalsePositives></FalsePositives><FalseNegatives></FalseNegatives><Documentable>false</Documentable><Mitigations></Mitigations><SeverityOverrideGuidance></SeverityOverrideGuidance><PotentialImpacts></PotentialImpacts><ThirdPartyTools></ThirdPartyTools><MitigationControl></MitigationControl><Responsibility></Responsibility><IAControls></IAControls>",
          "reference": {
            "title": "DPMS Target zOS CLSuperSession for ACF2",
            "publisher": "DISA",
            "type": "DPMS Target",
            "subject": "zOS CLSuperSession for ACF2",
            "identifier": "4117"
          },
          "ident": [
            {
              "+content": "V-22690",
              "+@system": "http://cyber.mil/legacy"
            },
            {
              "+content": "SV-27256",
              "+@system": "http://cyber.mil/legacy"
            },
            {
              "+content": "CCI-000381",
              "+@system": "http://cyber.mil/cci"
            }
          ],
          "fixtext": {
            "+content": "Ensure that the parameter options for member KLKINNAM for Version 3 of CL/SuperSession or  KLVINNAM for Version 2 of CL/SuperSession are coded to the below specifications.\n\n(Note: The data set identified below is an example of a possible installation. The actual data set is determined when the product is actually installed on a system through the product's installation guide and can be site specific.)\n\nReview the member KLKINNAM or KLVINNAM in the TLVPARM DD statement concatenation of the CL/SuperSession STC procedure. (This member is located in SYS3.OMEGAMON.qualifier.RLSPARM.) Ensure all session manager security parameters and control options are in compliance according to the following: \n\nDEFAULT DSNAME(SYS3.OMEGAMON.qualifier.RLSNAM) -\n      NORACF -\n      CLASSES=APPCLASS -\n      NODB -\n      EXIT=KLSA2NEV\n\n(The following is for z/OS CAC logon processing)\nDEFAULT DSNAME(SYS3.OMEGAMON.qualifier.RLSNAM) -\n      SAF -\n      CLASSES=APPCLASS -\n      NODB -\n      EXIT=KLSSFPTX",
            "+@fixref": "F-25948r952248_fix"
          },
          "fix": {
            "+@id": "F-25948r952248_fix"
          },
          "check": {
            "+@system": "C-25960r1041221_chk",
            "check-content-ref": {
              "+@href": "zOS_CLSuperSession_for_ACF2_STIG.xml",
              "+@name": "M"
            },
            "check-content": "If one of the following configuration settings is specified for each control point defined in the KLKINNAM member for Version 3 of CL/SuperSession or KLVINNAM member for Version 2 of CL/SuperSession, this is not a finding.\n\nDEFAULT DSNAME(SYS3.OMEGAMON.qualifier.RLSNAM) -\nNORACF -\nCLASSES=APPCLASS -\nNODB -\nEXIT=KLSA2NEV\n\n(The following is for z/OS CAC logon processing)\nDEFAULT DSNAME(SYS3.OMEGAMON.qualifier.RLSNAM) -\nSAF -\nCLASSES=APPCLASS -\nNODB -\nEXIT=KLSSFPTX"
          }
        }
      },
      {
        "+@id": "V-224288",
        "title": "SRG-OS-000018",
        "description": "<GroupDescription></GroupDescription>",
        "Rule": {
          "+@id": "SV-224288r1041225_rule",
          "+@weight": "10.0",
          "+@severity": "medium",
          "version": "ZCLSA043",
          "title": "CL/SuperSession APPCLASS member is not configured in accordance with the proper security requirements.",
          "description": "<VulnDiscussion>CL/SuperSession configuration/parameters control the security and operational characteristics of products. If these parameter values are improperly specified, security and operational controls may be weakened. This exposure may threaten the availability of the product applications, and compromise the confidentiality of customer data.</VulnDiscussion><FalsePositives></FalsePositives><FalseNegatives></FalseNegatives><Documentable>false</Documentable><Mitigations></Mitigations><SeverityOverrideGuidance></SeverityOverrideGuidance><PotentialImpacts></PotentialImpacts><ThirdPartyTools></ThirdPartyTools><MitigationControl></MitigationControl><Responsibility></Responsibility><IAControls></IAControls>",
          "reference": {
            "title": "DPMS Target zOS CLSuperSession for ACF2",
            "publisher": "DISA",
            "type": "DPMS Target",
            "subject": "zOS CLSuperSession for ACF2",
            "identifier": "4117"
          },
          "ident": [
            {
              "+content": "V-22691",
              "+@system": "http://cyber.mil/legacy"
            },
            {
              "+content": "SV-27259",
              "+@system": "http://cyber.mil/legacy"
            },
            {
              "+content": "CCI-000381",
              "+@system": "http://cyber.mil/cci"
            }
          ],
          "fixtext": {
            "+content": "The systems programmer and ISSO will ensure that the parameter options for member APPCLASS are coded to the below specifications.\n\nReview the member APPCLASS in the TLVPARM DD statement concatenation of the CL/SuperSession STC procedure. (This member is located in SYS3.OMEGAMON.qualifier.RLSPARM.) Ensure all session manager security parameters and control options are in compliance according to the following: \n\nVGWAPLST EXTERNAL=APL",
            "+@fixref": "F-25949r1041224_fix"
          },
          "fix": {
            "+@id": "F-25949r1041224_fix"
          },
          "check": {
            "+@system": "C-25961r1041223_chk",
            "check-content-ref": {
              "+@href": "zOS_CLSuperSession_for_ACF2_STIG.xml",
              "+@name": "M"
            },
            "check-content": "a) Review the member APPCLASS in the TLVPARM DD statement concatenation of the CL/SuperSession STC procedure.  (This member is located in SYS3.OMEGAMON.qualifier.RLSPARM.)\n\nAutomated Analysis\nRefer to the following report produced by the z/OS Data Collection:\n\n- PDI(ZCLS0043)\n\nb) If the parameters for the member APPCLASS are configured as follows, there is no finding:\n\n\tVGWAPLST EXTERNAL=APL\n\nc) If the parameters for the member APPCLASS are not configured as specified in (b) above, this is a finding."
          }
        }
      }
    ]
  }
}
